{
  "timestamp": "2026-02-12T05:00:03.129600+00:00",
  "period_hours": 24,
  "shared_topics": [
    {
      "topic": "reddit",
      "agents": [
        "main",
        "commerce",
        "researcher",
        "dev"
      ],
      "signal": "collaboration"
    },
    {
      "topic": "notion",
      "agents": [
        "main",
        "commerce",
        "researcher",
        "dev"
      ],
      "signal": "collaboration"
    },
    {
      "topic": "invoice tracker",
      "agents": [
        "main",
        "commerce",
        "researcher",
        "dev"
      ],
      "signal": "collaboration"
    },
    {
      "topic": "gumroad",
      "agents": [
        "main",
        "commerce",
        "researcher",
        "dev"
      ],
      "signal": "collaboration"
    },
    {
      "topic": "template",
      "agents": [
        "main",
        "commerce",
        "researcher",
        "dev"
      ],
      "signal": "collaboration"
    },
    {
      "topic": "newsletter",
      "agents": [
        "main",
        "commerce",
        "researcher",
        "dev"
      ],
      "signal": "collaboration"
    },
    {
      "topic": "pinterest",
      "agents": [
        "main",
        "commerce",
        "researcher"
      ],
      "signal": "collaboration"
    },
    {
      "topic": "polymarket",
      "agents": [
        "main",
        "researcher",
        "dev"
      ],
      "signal": "collaboration"
    },
    {
      "topic": "etsy",
      "agents": [
        "main",
        "commerce",
        "researcher"
      ],
      "signal": "collaboration"
    },
    {
      "topic": "nate calloway",
      "agents": [
        "main",
        "researcher",
        "dev"
      ],
      "signal": "collaboration"
    },
    {
      "topic": "twitter",
      "agents": [
        "main",
        "commerce",
        "researcher"
      ],
      "signal": "collaboration"
    },
    {
      "topic": "shopify",
      "agents": [
        "main",
        "commerce"
      ],
      "signal": "collaboration"
    },
    {
      "topic": "instagram",
      "agents": [
        "main",
        "commerce"
      ],
      "signal": "collaboration"
    },
    {
      "topic": "stripe",
      "agents": [
        "main",
        "commerce"
      ],
      "signal": "collaboration"
    },
    {
      "topic": "youtube",
      "agents": [
        "main",
        "commerce"
      ],
      "signal": "collaboration"
    }
  ],
  "shared_tools": [
    {
      "tool": "read",
      "agents": [
        "main",
        "commerce",
        "researcher",
        "dev",
        "growth",
        "analytics",
        "ops"
      ]
    },
    {
      "tool": "write",
      "agents": [
        "main",
        "commerce",
        "researcher"
      ]
    },
    {
      "tool": "web_search",
      "agents": [
        "main",
        "commerce",
        "researcher"
      ]
    },
    {
      "tool": "web_fetch",
      "agents": [
        "main",
        "commerce",
        "researcher"
      ]
    },
    {
      "tool": "exec",
      "agents": [
        "main",
        "commerce"
      ]
    },
    {
      "tool": "session_status",
      "agents": [
        "main",
        "commerce"
      ]
    },
    {
      "tool": "edit",
      "agents": [
        "main",
        "commerce"
      ]
    },
    {
      "tool": "browser",
      "agents": [
        "main",
        "commerce"
      ]
    },
    {
      "tool": "sessions_send",
      "agents": [
        "main",
        "commerce"
      ]
    }
  ],
  "agent_error_counts": {
    "main": 13
  },
  "active_agents": [
    "main",
    "commerce",
    "researcher",
    "dev",
    "growth",
    "analytics",
    "ops"
  ]
}
